{
  "scan_type": "country_region",
  "scope": {
    "country": "US",
    "region": "GU",
    "city": null
  },
  "queries_used": [
    "\"overnight summer camp\" Guam",
    "\"residential summer camp\" Guam",
    "\"family camp\" Guam",
    "\"youth retreat\" Guam overnight",
    "site:.edu Guam pre-college residential"
  ],
  "next_queries": [
    "retry web search using alternate engine or API",
    "inspect major university and college sites in Guam directly for summer/residential programs",
    "examine local government youth and recreation department web pages for relevant leads",
    "search for summer camp associations (regional or Pacific territory) that may index Guam programs"
  ],
  "candidates": []
}