{
  "scan_type": "country_region",
  "scope": {
    "country": "US",
    "region": "MI",
    "city": null
  },
  "queries_used": [
    "overnight summer camp Michigan",
    "residential summer camp Michigan",
    "family camp Michigan",
    "youth retreat Michigan overnight",
    "site:.edu Michigan pre-college residential"
  ],
  "next_queries": [],
  "candidates": [
    {
      "candidate_name": "Camp Walden Michigan",
      "translated_name_hint": null,
      "operator_name": null,
      "venue_name": "Camp Walden",
      "city": null,
      "region": "MI",
      "country": "US",
      "canonical_url": "https://campwaldenmi.com/",
      "supporting_urls": ["https://campwaldenmi.com/dates-rates/", "https://campwaldenmi.com/faqs/"],
      "directory_source_url": null,
      "source_language": "en",
      "program_family_tags": ["traditional", "overnight"],
      "camp_type_tags": ["coed", "lake", "nature"],
      "candidate_shape": "single_venue_candidate",
      "priority_flags": {"likely_college_precollege": false, "likely_one_week_plus": true},
      "duration_hint_text": "2 weeks, 4 weeks, and other multi-week sessions",
      "overnight_evidence": {"snippet": "My son went to Walden as his (and our) first overnight experience.", "url": "https://campwaldenmi.com/"},
      "recent_activity_evidence": {"snippet": "Registration opens September 18 for returning families and to the public on September 27. See our 2026 session dates and rates.", "url": "https://campwaldenmi.com/dates-rates/", "date_text": "2026"},
      "notes": null,
      "validation_needs": [],
      "confidence": "high"
    },
    {
      "candidate_name": "Howell Nature Center Camp Wonder Overnight Camps",
      "translated_name_hint": null,
      "operator_name": "Howell Nature Center",
      "venue_name": "Howell Nature Center",
      "city": "Howell",
      "region": "MI",
      "country": "US",
      "canonical_url": "https://www.howellnaturecenter.org/camp-wonder/soa-overnight-camps/",
      "supporting_urls": ["https://www.howellnaturecenter.org/camp-wonder/", "https://www.howellnaturecenter.org/wordpress/wp-content/uploads/2025/03/Print2025-BrochureCampWonder-C.pdf"],
      "directory_source_url": null,
      "source_language": "en",
      "program_family_tags": ["overnight", "nature"],
      "camp_type_tags": ["coed", "outdoor", "adventure"],
      "candidate_shape": "single_venue_candidate",
      "priority_flags": {"likely_college_precollege": false, "likely_one_week_plus": true},
      "duration_hint_text": "6-night overnight sessions",
      "overnight_evidence": {"snippet": "transformative overnight experience! Explorers, Adventurers, Trailblazers... 6-night camp programs", "url": "https://www.howellnaturecenter.org/camp-wonder/soa-overnight-camps/"},
      "recent_activity_evidence": {"snippet": "2025 and 2026 overnight camp sessions with registration brochure available.", "url": "https://www.howellnaturecenter.org/wordpress/wp-content/uploads/2025/03/Print2025-BrochureCampWonder-C.pdf", "date_text": "2025-2026"},
      "notes": null,
      "validation_needs": [],
      "confidence": "high"
    },
    {
      "candidate_name": "Cedar Lodge Summer Camp",
      "translated_name_hint": null,
      "operator_name": null,
      "venue_name": "Cedar Lodge",
      "city": "Lawrence",
      "region": "MI",
      "country": "US",
      "canonical_url": "https://www.cedarlodge.com/summer-camp/",
      "supporting_urls": ["https://www.cedarlodge.com/rates-and-dates/", "https://www.cedarlodge.com/our-facilities/"],
      "directory_source_url": null,
      "source_language": "en",
      "program_family_tags": ["overnight", "equestrian", "family"],
      "camp_type_tags": ["coed", "horse", "nature"],
      "candidate_shape": "single_venue_candidate",
      "priority_flags": {"likely_college_precollege": false, "likely_one_week_plus": true},
      "duration_hint_text": "Overnight, Day, and 1 to 7 week stays (typically Sunday to Sunday)",
      "overnight_evidence": {"snippet": "Cedar Lodge is primarily an overnight coed summer camp offering 6 weeks of residential camp for children from age 7-16.", "url": "https://www.cedarlodge.com/summer-camp/"},
      "recent_activity_evidence": {"snippet": "Cedar Lodge 2026. 50+ years of camping experience. Session info for current/next cycle.", "url": "https://www.cedarlodge.com/summer-camp/", "date_text": "2026"},
      "notes": null,
      "validation_needs": [],
      "confidence": "high"
    },
    {
      "candidate_name": "YMCA Camp Ohiyesa",
      "translated_name_hint": null,
      "operator_name": "YMCA of Metropolitan Detroit",
      "venue_name": "YMCA Camp Ohiyesa",
      "city": "Holly",
      "region": "MI",
      "country": "US",
      "canonical_url": "https://ymcadetroit.org/ohiyesa/",
      "supporting_urls": ["https://ymcadetroit.org/programs/camp/overnight-camp/overnight-camp-3/"],
      "directory_source_url": null,
      "source_language": "en",
      "program_family_tags": ["overnight", "traditional"],
      "camp_type_tags": ["coed", "lake", "adventure"],
      "candidate_shape": "single_venue_candidate",
      "priority_flags": {"likely_college_precollege": false, "likely_one_week_plus": true},
      "duration_hint_text": "One week+ and daily overnight options for ages 5-teen",
      "overnight_evidence": {"snippet": "Ohiyesa Overnight camp is an American rite of passage... We offer day and overnight camp.", "url": "https://ymcadetroit.org/ohiyesa/"},
      "recent_activity_evidence": {"snippet": "Registration for the 2026 camp season is open now!", "url": "https://ymcadetroit.org/ohiyesa/", "date_text": "2026"},
      "notes": null,
      "validation_needs": [],
      "confidence": "high"
    },
    {
      "candidate_name": "Interlochen Arts Camp",
      "translated_name_hint": null,
      "operator_name": "Interlochen Center for the Arts",
      "venue_name": "Interlochen Arts Camp",
      "city": "Interlochen",
      "region": "MI",
      "country": "US",
      "canonical_url": "https://www.interlochen.org/",
      "supporting_urls": ["https://www.interlochen.org/art-summer-camp"],
      "directory_source_url": null,
      "source_language": "en",
      "program_family_tags": ["arts", "overnight", "pre-college-academic"],
      "camp_type_tags": ["coed", "music", "visual_arts", "dance", "writing", "film", "global"],
      "candidate_shape": "single_venue_candidate",
      "priority_flags": {"likely_college_precollege": true, "likely_one_week_plus": true},
      "duration_hint_text": "Multi-week residential sessions; grades 3-12, focused arts tracks",
      "overnight_evidence": {"snippet": "Interlochen Arts Camp has summer programs for every young artist. Overnight residential camp for grades 3-12.", "url": "https://www.interlochen.org/art-summer-camp"},
      "recent_activity_evidence": {"snippet": "Registration for summer 2026 arts camp is open. Recent events calendar is active.", "url": "https://www.interlochen.org/", "date_text": "2026"},
      "notes": null,
      "validation_needs": [],
      "confidence": "high"
    }
  ]
}
